[
    {
        "call": "W5MMW",
        "gridsquare": "EM75",
        "mode": "FT8",
        "rst_sent": -10,
        "rst_rcvd": -18,
        "qso_date": "2024-08-20",
        "time_on": "23:48:30",
        "qso_date_off": "2024-08-20",
        "time_off": "2349-02-09",
        "band": "20m",
        "freq": 14.086485,
        "station_callsign": "KM6KFX",
        "my_gridsquare": "CM87vt",
        "comment": "FT8  Sent: -10  Rcvd: -18  Distance: 2058 mi"
    },
    {
        "call": "W5MMW",
        "gridsquare": "EM75",
        "mode": "JT65",
        "rst_sent": -19,
        "rst_rcvd": -16,
        "qso_date": "2024-08-23",
        "time_on": "23:52:00",
        "qso_date_off": "2024-08-23",
        "time_off": "235750",
        "band": "10m",
        "freq": 28.091776,
        "station_callsign": "KM6KFX",
        "my_gridsquare": "CM87vt",
        "comment": "JT65  Sent: -19  Rcvd: -16  Distance: 2058 mi"
    },
    {
        "call": "W5MMW",
        "gridsquare": "EM75",
        "mode": "FT8",
        "rst_sent": -1,
        "rst_rcvd": -7,
        "qso_date": "2024-08-24",
        "time_on": "00:09:30",
        "qso_date_off": "2024-08-24",
        "time_off": "0010-02-09",
        "band": "20m",
        "freq": 14.061776,
        "station_callsign": "KM6KFX",
        "my_gridsquare": "CM87vt",
        "comment": "FT8  Sent: -01  Rcvd: -07  Distance: 2058 mi"
    },
    {
        "call": "W5MMW",
        "gridsquare": "EM75",
        "mode": "FT8",
        "rst_sent": -3,
        "rst_rcvd": -17,
        "qso_date": "2024-08-24",
        "time_on": "02:07:30",
        "qso_date_off": "2024-08-24",
        "time_off": "0210-05-09",
        "band": "40m",
        "freq": 7.081776,
        "station_callsign": "KM6KFX",
        "my_gridsquare": "CM87vt",
        "comment": "FT8  Sent: -03  Rcvd: -17  Distance: 2058 mi"
    },
    {
        "call": "W5MMW",
        "gridsquare": "EM75",
        "mode": "FT8",
        "rst_sent": -11,
        "rst_rcvd": -24,
        "qso_date": "2024-09-02",
        "time_on": "23:51:15",
        "qso_date_off": "2024-09-02",
        "time_off": "2357-01-06",
        "band": "20m",
        "freq": 14.075533,
        "station_callsign": "KM6KFX",
        "my_gridsquare": "CM87vt",
        "comment": "FT8  Sent: -11  Rcvd: -24  Distance: 2058 mi"
    },
    {
        "call": "W5MMW",
        "gridsquare": "EM75",
        "mode": "FT8",
        "rst_sent": -14,
        "rst_rcvd": -18,
        "qso_date": "2024-09-13",
        "time_on": "22:08:45",
        "qso_date_off": "2024-09-13",
        "time_off": "2210-01-05",
        "band": "20m",
        "freq": 14.076399,
        "station_callsign": "KM6KFX",
        "my_gridsquare": "CM87vt",
        "comment": "FT8  Sent: -14  Rcvd: -18  Distance: 2058 mi"
    },
    {
        "call": "W5MMW",
        "gridsquare": "EM75",
        "mode": "MFSK",
        "submode": "FT4",
        "rst_sent": -7,
        "rst_rcvd": -13,
        "qso_date": "2024-10-15",
        "time_on": "04:41:37",
        "qso_date_off": "2024-10-15",
        "time_off": "044207",
        "band": "20m",
        "freq": 14.081501,
        "station_callsign": "KM6KFX",
        "my_gridsquare": "CM87vt",
        "comment": "FT4  Sent: -07  Rcvd: -13  Distance: 2058 mi"
    }
]